tglogger/__init__.py
tglogger/formatter.py
tglogger/handler.py
tglogger/request.py
tglogger-0.1.1a3.dist-info/LICENSE.txt
tglogger-0.1.1a3.dist-info/METADATA
tglogger-0.1.1a3.dist-info/WHEEL
tglogger-0.1.1a3.dist-info/top_level.txt
tglogger-0.1.1a3.dist-info/RECORD
