Metadata-Version: 2.1
Name: tglogger
Version: 0.1.1a3
Summary: tglogger is a logger handler and formatter for Telegram bots.
Home-page: https://github.com/erayerdin/tglogger
Author: Eray Erdin
Author-email: eraygezer.94@gmail.com
License: Apache License 2.0
Download-URL: https://github.com/erayerdin/tglogger/archive/v0.1.1a3.tar.gz
Keywords: telegram messaging communication logging
Platform: UNKNOWN
Classifier: Development Status :: 3 - Alpha
Classifier: Intended Audience :: Developers
Classifier: Intended Audience :: System Administrators
Classifier: License :: OSI Approved :: Apache Software License
Classifier: Programming Language :: Python :: 3 :: Only
Classifier: Programming Language :: Python :: 3.5
Classifier: Programming Language :: Python :: 3.6
Classifier: Programming Language :: Python :: 3.7
Classifier: Programming Language :: Python :: 3.8
Classifier: Framework :: Django :: 1.11
Classifier: Framework :: Django :: 2.0
Classifier: Framework :: Django :: 2.1
Classifier: Framework :: Django :: 2.2
Classifier: Topic :: Communications :: Chat
Classifier: Topic :: System :: Logging
Classifier: Topic :: System :: Monitoring
Requires-Dist: requests (>=2&<3)
